opengrapher/__init__.py
opengrapher_useragent-0.2.1.dist-info/LICENSE
opengrapher_useragent-0.2.1.dist-info/METADATA
opengrapher_useragent-0.2.1.dist-info/WHEEL
opengrapher_useragent-0.2.1.dist-info/entry_points.txt
opengrapher_useragent-0.2.1.dist-info/top_level.txt
opengrapher_useragent-0.2.1.dist-info/RECORD
