Metadata-Version: 2.1
Name: opengrapher-useragent
Version: 0.2.1
Summary: Utility for parsing the OpenGraph tags - with customizable User-Agent headers
Home-page: https://github.com/rev138/opengrapher/tree/useragent
Author: Brian O'Donnell
Author-email: brian@pancrypticon.net
License: MIT
Keywords: opengraph
Platform: UNKNOWN
Classifier: Development Status :: 3 - Alpha
Classifier: Intended Audience :: Developers
Classifier: Topic :: Text Processing :: Markup :: HTML
Classifier: Topic :: Software Development :: Libraries :: Python Modules
Classifier: License :: OSI Approved :: MIT License
Classifier: Programming Language :: Python :: 3 :: Only
Requires-Python: >=3.4
Requires-Dist: beautifulsoup4
Requires-Dist: requests
